py_deploy/__init__.py
py_deploy/cli_commands.py
py_deploy-1.0.1.dist-info/LICENSE
py_deploy-1.0.1.dist-info/METADATA
py_deploy-1.0.1.dist-info/WHEEL
py_deploy-1.0.1.dist-info/entry_points.txt
py_deploy-1.0.1.dist-info/top_level.txt
py_deploy-1.0.1.dist-info/RECORD
