Metadata-Version: 2.1
Name: py-deploy
Version: 1.0.1
Summary: A simple deployer cmd tool
Home-page: https://github.com/velykanov/py_deploy
Author: Mykyta Velykanov
Author-email: nikitavelykanov@gmail.com
License: UNKNOWN
Platform: UNKNOWN
Classifier: Programming Language :: Python :: 3
Classifier: License :: OSI Approved :: MIT License
Classifier: Operating System :: OS Independent
Requires-Python: >=3.6
